LICENSE
MANIFEST.in
README.rst
setup.py
assets/screenshot.png
snipping/__init__.py
snipping/application.py
snipping/driver.py
snipping/engine.py
snipping/key_bindings.py
snipping/layout.py
snipping/main.py
snipping/py_driver.py
snipping.egg-info/PKG-INFO
snipping.egg-info/SOURCES.txt
snipping.egg-info/dependency_links.txt
snipping.egg-info/entry_points.txt
snipping.egg-info/requires.txt
snipping.egg-info/top_level.txt
snipping/prompt_toolkit/__init__.py
snipping/prompt_toolkit/buffers.py
snipping/prompt_toolkit/key_binding.py
snipping/prompt_toolkit/layout.py
snipping/prompt_toolkit/style.py
snipping/tests/__init__.py
snipping/tests/utils/__init__.py
snipping/tests/utils/test_fileutil.py
snipping/tests/utils/test_strutil.py
snipping/utils/__init__.py
snipping/utils/executil.py
snipping/utils/fileutil.py
snipping/utils/importutil.py
snipping/utils/strutil.py