Metadata-Version: 1.0
Name: snipping
Version: 0.2
Summary: Edit and run snippet in real time
Home-page: https://github.com/yittg/snipping
Author: Yi Tang
Author-email: ssnailtang@gmail.com
License: MIT
Platform: UNKNOWN
